hello_robot_stretch_body-0.7.30.dist-info/licenses/LICENSE.md
stretch_body/__init__.py
stretch_body/arm.py
stretch_body/base.py
stretch_body/cobbs_framing.py
stretch_body/device.py
stretch_body/dynamixel_XL430.py
stretch_body/dynamixel_X_chain.py
stretch_body/dynamixel_hello_XL430.py
stretch_body/end_of_arm.py
stretch_body/end_of_arm_tools.py
stretch_body/gamepad_controller.py
stretch_body/gamepad_joints.py
stretch_body/gamepad_teleop.py
stretch_body/gripper_conversion.py
stretch_body/head.py
stretch_body/hello_utils.py
stretch_body/lift.py
stretch_body/pimu.py
stretch_body/prismatic_joint.py
stretch_body/rerun_plot.py
stretch_body/robot.py
stretch_body/robot_collision.py
stretch_body/robot_monitor.py
stretch_body/robot_params.py
stretch_body/robot_params_RE1V0.py
stretch_body/robot_params_RE2V0.py
stretch_body/robot_params_SE3.py
stretch_body/robot_trace.py
stretch_body/scope.py
stretch_body/stepper.py
stretch_body/stretch_gripper.py
stretch_body/trajectories.py
stretch_body/transport.py
stretch_body/version.py
stretch_body/wacc.py
stretch_body/wrist_pitch.py
stretch_body/wrist_roll.py
stretch_body/wrist_yaw.py
test/__init__.py
test/test_arm.py
test/test_base.py
test/test_collisions.py
test/test_device.py
test/test_dxl_comms.py
test/test_dxl_sine_vel.py
test/test_dxl_vel.py
test/test_dynamixel_XL430.py
test/test_dynamixel_hello_XL430.py
test/test_end_of_arm.py
test/test_end_of_arm_tools.py
test/test_head.py
test/test_hello_utils.py
test/test_lift.py
test/test_pimu.py
test/test_robot.py
test/test_robot_params.py
test/test_steppers.py
test/test_stretch_gripper.py
test/test_sync.py
test/test_timing_stats.py
test/test_trajectories.py
test/test_wait_command.py
test/test_wrist_yaw.py
hello_robot_stretch_body-0.7.30.dist-info/METADATA
hello_robot_stretch_body-0.7.30.dist-info/WHEEL
hello_robot_stretch_body-0.7.30.dist-info/top_level.txt
hello_robot_stretch_body-0.7.30.dist-info/RECORD
