Metadata-Version: 2.4
Name: hello-robot-stretch-body
Version: 0.7.30
Summary: Stretch Body low level Python API
Home-page: https://github.com/hello-robot/stretch_body
Author: Hello Robot Inc.
Author-email: support@hello-robot.com
Classifier: Programming Language :: Python :: 3
Classifier: Operating System :: OS Independent
Classifier: License :: OSI Approved :: GNU Lesser General Public License v3 (LGPLv3)
License-File: LICENSE.md
Requires-Dist: numpy>=1.24
Requires-Dist: scipy
Requires-Dist: matplotlib
Requires-Dist: ipython
Requires-Dist: pandas
Requires-Dist: sympy
Requires-Dist: nose
Requires-Dist: inputs
Requires-Dist: drawnow
Requires-Dist: rplidar-roboticia
Requires-Dist: snakeviz
Requires-Dist: pyusb
Requires-Dist: SpeechRecognition
Requires-Dist: pixel-ring
Requires-Dist: click
Requires-Dist: cma
Requires-Dist: colorama
Requires-Dist: filelock
Requires-Dist: scikit-image
Requires-Dist: open3d
Requires-Dist: pyrealsense2
Requires-Dist: pathlib
Requires-Dist: psutil
Requires-Dist: gitpython
Requires-Dist: urchin
Requires-Dist: urdf_parser_py
Requires-Dist: opencv-contrib-python
Requires-Dist: renamed-opencv-python-inference-engine; python_version >= "3.0.0"
Requires-Dist: jupyter
Requires-Dist: transforms3d>=0.4.2
Requires-Dist: dynamixel-sdk
Requires-Dist: pyyaml>=5.1
Requires-Dist: hello-robot-stretch-tool-share>=0.3.3
Requires-Dist: hello-robot-stretch-factory>=0.3.5
Requires-Dist: hello-robot-stretch-body-tools>=0.4.2
Requires-Dist: hello-robot-stretch-urdf>=0.0.19
Requires-Dist: aioserial
Requires-Dist: meshio
Requires-Dist: numpy-stl
Requires-Dist: pyrender
Requires-Dist: chime
Dynamic: author
Dynamic: author-email
Dynamic: classifier
Dynamic: description
Dynamic: description-content-type
Dynamic: home-page
Dynamic: license-file
Dynamic: requires-dist
Dynamic: summary
